auth_key_manager/__init__.py
auth_key_manager/__version__.py
auth_key_manager/update_checker.py
auth_key_manager-0.0.1.dist-info/LICENSE
auth_key_manager-0.0.1.dist-info/METADATA
auth_key_manager-0.0.1.dist-info/WHEEL
auth_key_manager-0.0.1.dist-info/top_level.txt
auth_key_manager-0.0.1.dist-info/RECORD
