Metadata-Version: 2.1
Name: auth_key_manager
Version: 0.0.1
Summary: A robust and flexible license key management system for Python applications, enabling secure license validation, renewal, and revocation with ease.
Home-page: https://github.com/AuthForge/AuthKeyManager
Author: IbrahimBkt
Author-email: AuthForge@outlook.com
Classifier: Programming Language :: Python :: 3
Classifier: License :: OSI Approved :: MIT License
Classifier: Operating System :: OS Independent
Requires-Python: >=3.6
License-File: LICENSE
Requires-Dist: mysql-connector-python
Requires-Dist: pymongo
Requires-Dist: requests
